[
 {
  "name": "ナイトヘッド",
  "compose": "自身のレベル分の固定ダメージ。ノーマルタイプには無効だが、それ以外のタイプ相性は無視。",
  "ref": "自分のレベルと同じ値の固定ダメージを与える。『ノーマル』タイプには無効だが、それ以外のタイプ相性の影響を受けない。"
 },
 {
  "name": "いやなおと",
  "compose": "音技。敵のぼうぎょを2段階低下。みがわりを貫通。",
  "ref": "相手の『ぼうぎょ』ランクを2段階下げる。音系の技。相手の『みがわり』状態を貫通する。"
 },
 {
  "name": "かげぶんしん",
  "compose": "自身の回避率を1段階上昇。",
  "ref": "自分の回避率を1段階上げる。"
 },
 {
  "name": "じこさいせい",
  "compose": "最大HPの50%回復。",
  "ref": "HPが最大HPの半分回復する。"
 },
 {
  "name": "ちいさくなる",
  "compose": "自身の回避率を2段階上昇。ただし、のしかかり/ヒートスタンプ/フライングプレスなど一部の技は必中・威力2倍で受ける。",
  "ref": "自分の回避率を2段階上げる。ただし、技『サンダーダイブ』『のしかかり』『ふみつけ』『ドラゴンダイブ』『ハードローラー』『ハイパーダーククラッシャー』『フライングプレス』『ヒートスタンプ』『ヘビーボンバー』は必ず命中し威力2倍で受けるようになってしまう(ヒートスタンプは第6世代以降、ヘビーボンバーは第7世代以降。なお、ゴーストダイブは第6世代のみ)。"
 },
 {
  "name": "あやしいひかり",
  "compose": "敵を1〜4ターン、こんらん化。",
  "ref": "相手を1〜4ターンの間『こんらん』状態にする。"
 },
 {
  "name": "ひかりのかべ",
  "compose": "5ターン、敵の特殊攻撃ダメージを半減。味方複数時は2/3。急所は軽減対象外。交代後も維持。",
  "ref": "5ターンの間、相手の特殊攻撃のダメージを半分にする。味方が複数の場合は半分ではなく2/3になる。急所に当たった場合は軽減されない。交代しても効果は続く。"
 },
 {
  "name": "くろいきり",
  "compose": "全ポケモンの能力ランクをリセット。",
  "ref": "すべてのポケモンの能力ランクの変化を元に戻す。"
 },
 {
  "name": "リフレクター",
  "compose": "5ターン、敵の物理攻撃ダメージを半減。味方複数時は2/3。急所は軽減対象外。交代後も維持。",
  "ref": "5ターンの間、相手の物理攻撃のダメージを半分にする。味方が複数の場合は半分ではなく2/3になる。急所に当たった場合は軽減されない。交代しても効果は続く。"
 },
 {
  "name": "きあいだめ",
  "compose": "自身をきゅうしょアップ+2に。すでに発動中なら失敗。",
  "ref": "『きゅうしょアップ』状態(急所ランク2段階)となり、今後自分の技が急所に当たりやすくなる。(すでに『きゅうしょアップ』状態の時は失敗する)"
 },
 {
  "name": "じばく",
  "compose": "攻撃後、自身がひんし化。",
  "ref": "攻撃後、自分が『ひんし』状態になる。"
 },
 {
  "name": "だいもんじ",
  "compose": "確率10%で敵をやけど化。",
  "ref": "10%の確率で相手を『やけど』状態にする。"
 },
 {
  "name": "たきのぼり",
  "compose": "確率20%で敵をひるませる。",
  "ref": "20%の確率で相手をひるませる。"
 },
 {
  "name": "ドわすれ",
  "compose": "自身のとくぼうを2段階上昇。",
  "ref": "自分の『とくぼう』ランクを2段階上げる。"
 },
 {
  "name": "とびひざげり",
  "compose": "外れるか失敗時、自身のHPを最大HP/2消費。",
  "ref": "攻撃が外れたり、相手の技『まもる』などで失敗すると、自分の最大HPの半分のダメージを自分が受ける。"
 },
 {
  "name": "へびにらみ",
  "compose": "敵をまひ化。でんきタイプには無効。",
  "ref": "相手を『まひ』状態にする。『でんき』タイプには無効。"
 },
 {
  "name": "きゅうけつ",
  "compose": "与えたダメージの1/2、自身のHPを回復。",
  "ref": "相手に与えたダメージの半分だけ自分のHPが回復する。"
 },
 {
  "name": "ゴッドバード",
  "compose": "急所ランク+1。1ターン目で溜め、2ターン目に攻撃。30%でひるみ。",
  "ref": "1ターン目は攻撃せずに、2ターン目で攻撃する。30%の確率で相手をひるませる。急所に当たりやすい(急所ランク:+1)。"
 },
 {
  "name": "へんしん",
  "compose": "敵に変身。HP・持ち物・状態異常を除く全要素をコピー。技PPは全5。交代で解除。",
  "ref": "一時的に、相手と同じナンバー・グラフィックス・能力値・個体値・ランク・特性・技になる。ただしHP・持ち物・状態異常などはコピーされずそのままとなり、技のPPはすべて5になる。交代すると元に戻る。ダイマックスしている相手をコピーすると、元のポケモンの姿になる。"
 },
 {
  "name": "とける",
  "compose": "自身のぼうぎょを2段階上昇。",
  "ref": "自分の『ぼうぎょ』ランクを2段階上げる。"
 },
 {
  "name": "クラブハンマー",
  "compose": "急所ランク+1。",
  "ref": "急所に当たりやすい(急所ランク:+1)。"
 },
 {
  "name": "だいばくはつ",
  "compose": "攻撃後、自身がひんし化。",
  "ref": "攻撃後、自分が『ひんし』状態になる。"
 }
]