{
  "generated": "review",
  "total_moves": 490,
  "tags": [
    {
      "tag": "has_secondary_effect",
      "count": 474,
      "samples": [
        "ほのおのパンチ",
        "れいとうパンチ",
        "かみなりパンチ",
        "ハサミギロチン",
        "つるぎのまい"
      ]
    },
    {
      "tag": "other_misc",
      "count": 84,
      "samples": [
        "カウンター",
        "じわれ",
        "かげぶんしん",
        "ちいさくなる",
        "リフレクター"
      ]
    },
    {
      "tag": "pierce_substitute",
      "count": 21,
      "samples": [
        "ふきとばし",
        "ほえる",
        "うたう",
        "いやなおと",
        "いびき"
      ]
    },
    {
      "tag": "inflict_flinch",
      "count": 18,
      "samples": [
        "かみつく",
        "たきのぼり",
        "ゴッドバード",
        "いわなだれ",
        "いびき"
      ]
    },
    {
      "tag": "damage_only",
      "count": 16,
      "samples": [
        "はたく",
        "メガトンキック",
        "ハイドロポンプ",
        "ドリルくちばし",
        "メガホーン"
      ]
    },
    {
      "tag": "inflict_burn",
      "count": 16,
      "samples": [
        "ほのおのパンチ",
        "かえんほうしゃ",
        "だいもんじ",
        "ねっぷう",
        "おにび"
      ]
    },
    {
      "tag": "up_crit_rate",
      "count": 16,
      "samples": [
        "きあいだめ",
        "ゴッドバード",
        "クラブハンマー",
        "クロスチョップ",
        "ブレイズキック"
      ]
    },
    {
      "tag": "power_x1_2_if_iron_fist",
      "count": 14,
      "samples": [
        "ほのおのパンチ",
        "れいとうパンチ",
        "かみなりパンチ",
        "マッハパンチ",
        "ばくれつパンチ"
      ]
    },
    {
      "tag": "inflict_confuse",
      "count": 14,
      "samples": [
        "あばれる",
        "はなびらのまい",
        "あやしいひかり",
        "てんしのキッス",
        "げきりん"
      ]
    },
    {
      "tag": "inflict_paralysis",
      "count": 13,
      "samples": [
        "かみなりパンチ",
        "のしかかり",
        "しびれごな",
        "10まんボルト",
        "でんじは"
      ]
    },
    {
      "tag": "priority_up_1",
      "count": 13,
      "samples": [
        "でんこうせっか",
        "マッハパンチ",
        "ふいうち",
        "しんくうは",
        "バレットパンチ"
      ]
    },
    {
      "tag": "down_opp_attack_1",
      "count": 13,
      "samples": [
        "くすぐる",
        "つぶらなひとみ",
        "おたけび",
        "じゃれつく",
        "キングシールド"
      ]
    },
    {
      "tag": "ignore_type_effectiveness",
      "count": 12,
      "samples": [
        "ハサミギロチン",
        "つのドリル",
        "カウンター",
        "ちきゅうなげ",
        "じわれ"
      ]
    },
    {
      "tag": "prevent_target_switch",
      "count": 12,
      "samples": [
        "しめつける",
        "まきつく",
        "ほのおのうず",
        "くろいまなざし",
        "うずしお"
      ]
    },
    {
      "tag": "inflict_poison",
      "count": 12,
      "samples": [
        "どくのこな",
        "どくどく",
        "ヘドロばくだん",
        "どくどくのキバ",
        "どくづき"
      ]
    },
    {
      "tag": "never_miss",
      "count": 11,
      "samples": [
        "ふきとばし",
        "ほえる",
        "あくび",
        "シャドーパンチ",
        "つばめがえし"
      ]
    },
    {
      "tag": "up_self_speed_1",
      "count": 10,
      "samples": [
        "こうそくスピン",
        "げんしのちから",
        "りゅうのまい",
        "ちょうのまい",
        "ニトロチャージ"
      ]
    },
    {
      "tag": "up_self_special_attack_1",
      "count": 9,
      "samples": [
        "せいちょう",
        "げんしのちから",
        "めいそう",
        "チャージビーム",
        "ちょうのまい"
      ]
    },
    {
      "tag": "down_opp_defense_1",
      "count": 9,
      "samples": [
        "アイアンテール",
        "かみくだく",
        "ブレイククロー",
        "くすぐる",
        "シェルブレード"
      ]
    },
    {
      "tag": "doubles_only_ally_target",
      "count": 9,
      "samples": [
        "このゆびとまれ",
        "いかりのこな",
        "おさきにどうぞ",
        "りんしょう",
        "サイドチェンジ"
      ]
    },
    {
      "tag": "hit_2_to_5_times",
      "count": 8,
      "samples": [
        "ミサイルばり",
        "ボーンラッシュ",
        "タネマシンガン",
        "つららばり",
        "ロックブラスト"
      ]
    },
    {
      "tag": "down_opp_special_defense_1",
      "count": 8,
      "samples": [
        "サイコキネシス",
        "シャドーボール",
        "むしのさざめき",
        "きあいだま",
        "エナジーボール"
      ]
    },
    {
      "tag": "drain_half",
      "count": 8,
      "samples": [
        "きゅうけつ",
        "ギガドレイン",
        "ドレインパンチ",
        "ウッドホーン",
        "ドレインキッス"
      ]
    },
    {
      "tag": "down_opp_speed_1",
      "count": 8,
      "samples": [
        "こごえるかぜ",
        "がんせきふうじ",
        "マッドショット",
        "ローキック",
        "じならし"
      ]
    },
    {
      "tag": "down_opp_special_attack_1",
      "count": 8,
      "samples": [
        "むしのていこう",
        "バークアウト",
        "おたけび",
        "マジカルフレイム",
        "ムーンフォース"
      ]
    },
    {
      "tag": "self_bound_multi_turn",
      "count": 7,
      "samples": [
        "しめつける",
        "まきつく",
        "ほのおのうず",
        "うずしお",
        "すなじごく"
      ]
    },
    {
      "tag": "up_self_attack_1",
      "count": 7,
      "samples": [
        "せいちょう",
        "げんしのちから",
        "コメットパンチ",
        "ビルドアップ",
        "りゅうのまい"
      ]
    },
    {
      "tag": "up_self_defense_1",
      "count": 7,
      "samples": [
        "はがねのつばさ",
        "げんしのちから",
        "たくわえる",
        "コスモパワー",
        "ビルドアップ"
      ]
    },
    {
      "tag": "down_self_defense_1",
      "count": 7,
      "samples": [
        "ばかぢから",
        "インファイト",
        "からをやぶる",
        "スケイルノイズ",
        "スケイルショット"
      ]
    },
    {
      "tag": "power_x2_if_target_minimized",
      "count": 6,
      "samples": [
        "のしかかり",
        "ドラゴンダイブ",
        "ヘビーボンバー",
        "ヒートスタンプ",
        "フライングプレス"
      ]
    },
    {
      "tag": "recoil_1_3",
      "count": 6,
      "samples": [
        "すてみタックル",
        "ボルテッカー",
        "フレアドライブ",
        "ブレイブバード",
        "ウッドハンマー"
      ]
    },
    {
      "tag": "recharge_next_turn",
      "count": 6,
      "samples": [
        "はかいこうせん",
        "ブラストバーン",
        "ハイドロカノン",
        "ハードプラント",
        "ギガインパクト"
      ]
    },
    {
      "tag": "heal_self_half",
      "count": 6,
      "samples": [
        "じこさいせい",
        "ねがいごと",
        "なまける",
        "はねやすめ",
        "いやしのはどう"
      ]
    },
    {
      "tag": "priority_up_4",
      "count": 6,
      "samples": [
        "まもる",
        "みきり",
        "こらえる",
        "ニードルガード",
        "キングシールド"
      ]
    },
    {
      "tag": "set_weather",
      "count": 6,
      "samples": [
        "すなあらし",
        "あまごい",
        "にほんばれ",
        "エレキフィールド",
        "さむいギャグ"
      ]
    },
    {
      "tag": "priority_up_2",
      "count": 6,
      "samples": [
        "しんそく",
        "このゆびとまれ",
        "フェイント",
        "いかりのこな",
        "サイドチェンジ"
      ]
    },
    {
      "tag": "up_self_special_defense_1",
      "count": 6,
      "samples": [
        "げんしのちから",
        "たくわえる",
        "じゅうでん",
        "コスモパワー",
        "めいそう"
      ]
    },
    {
      "tag": "switch_self_out",
      "count": 6,
      "samples": [
        "とんぼがえり",
        "ボルトチェンジ",
        "すてゼリフ",
        "クイックターン",
        "しっぽきり"
      ]
    },
    {
      "tag": "charge_1_turn_invulnerable",
      "count": 5,
      "samples": [
        "そらをとぶ",
        "あなをほる",
        "ダイビング",
        "とびはねる",
        "ゴーストダイブ"
      ]
    },
    {
      "tag": "lock_3_turns",
      "count": 5,
      "samples": [
        "あばれる",
        "はなびらのまい",
        "げきりん",
        "さわぐ",
        "だいふんげき"
      ]
    },
    {
      "tag": "charge_1_turn",
      "count": 5,
      "samples": [
        "ソーラービーム",
        "ゴッドバード",
        "ソーラーブレード",
        "メテオビーム",
        "エレクトロビーム"
      ]
    },
    {
      "tag": "cost_self_hp_half",
      "count": 5,
      "samples": [
        "とびひざげり",
        "のろい",
        "はらだいこ",
        "てっていこうせん",
        "しっぽきり"
      ]
    },
    {
      "tag": "up_self_defense_2",
      "count": 5,
      "samples": [
        "とける",
        "てっぺき",
        "コットンガード",
        "ほおばる",
        "たてこもる"
      ]
    },
    {
      "tag": "protect_self",
      "count": 5,
      "samples": [
        "まもる",
        "みきり",
        "ニードルガード",
        "キングシールド",
        "トーチカ"
      ]
    },
    {
      "tag": "clear_hazards_and_binds",
      "count": 5,
      "samples": [
        "こうそくスピン",
        "フェイント",
        "きりばらい",
        "キラースピン",
        "おかたづけ"
      ]
    },
    {
      "tag": "cure_self_status_on_use",
      "count": 5,
      "samples": [
        "フレアドライブ",
        "ねっとう",
        "もえつきる",
        "ねっさのだいち",
        "シャカシャカほう"
      ]
    },
    {
      "tag": "inflict_freeze",
      "count": 4,
      "samples": [
        "れいとうパンチ",
        "れいとうビーム",
        "ふぶき",
        "こおりのキバ"
      ]
    },
    {
      "tag": "one_hit_ko",
      "count": 4,
      "samples": [
        "ハサミギロチン",
        "つのドリル",
        "じわれ",
        "ぜったいれいど"
      ]
    },
    {
      "tag": "force_switch_target",
      "count": 4,
      "samples": [
        "ふきとばし",
        "ほえる",
        "ともえなげ",
        "ドラゴンテール"
      ]
    },
    {
      "tag": "priority_down_6",
      "count": 4,
      "samples": [
        "ふきとばし",
        "ほえる",
        "ともえなげ",
        "ドラゴンテール"
      ]
    },
    {
      "tag": "rampage_2_3_turns",
      "count": 4,
      "samples": [
        "あばれる",
        "はなびらのまい",
        "げきりん",
        "だいふんげき"
      ]
    },
    {
      "tag": "self_locked_into_move",
      "count": 4,
      "samples": [
        "あばれる",
        "はなびらのまい",
        "げきりん",
        "だいふんげき"
      ]
    },
    {
      "tag": "inflict_sleep",
      "count": 4,
      "samples": [
        "うたう",
        "ねむりごな",
        "さいみんじゅつ",
        "あくび"
      ]
    },
    {
      "tag": "copy_target_stat_stages",
      "count": 4,
      "samples": [
        "へんしん",
        "じこあんじ",
        "なりきり",
        "ミラータイプ"
      ]
    },
    {
      "tag": "priority_up_3",
      "count": 4,
      "samples": [
        "ねこだまし",
        "ワイドガード",
        "ファストガード",
        "はやてがえし"
      ]
    },
    {
      "tag": "power_x2_if_target_statused",
      "count": 4,
      "samples": [
        "からげんき",
        "ベノムショック",
        "たたりめ",
        "ひゃっきやこう"
      ]
    },
    {
      "tag": "down_opp_special_defense_2",
      "count": 4,
      "samples": [
        "うそなき",
        "きんぞくおん",
        "アシッドボム",
        "ルミナコリジョン"
      ]
    },
    {
      "tag": "down_self_special_defense_1",
      "count": 4,
      "samples": [
        "インファイト",
        "からをやぶる",
        "ぶちかまし",
        "アーマーキャノン"
      ]
    },
    {
      "tag": "hit_2_times",
      "count": 4,
      "samples": [
        "ダブルアタック",
        "ドラゴンアロー",
        "ダブルウイング",
        "ツインビーム"
      ]
    },
    {
      "tag": "change_target_type",
      "count": 4,
      "samples": [
        "みずびたし",
        "もりののろい",
        "ハロウィン",
        "まほうのこな"
      ]
    },
    {
      "tag": "set_field",
      "count": 4,
      "samples": [
        "グラスフィールド",
        "ミストフィールド",
        "エレキフィールド",
        "サイコフィールド"
      ]
    },
    {
      "tag": "no_effect_on_ghost",
      "count": 3,
      "samples": [
        "ハサミギロチン",
        "つのドリル",
        "いかりのまえば"
      ]
    },
    {
      "tag": "power_x2_if_target_diving",
      "count": 3,
      "samples": [
        "なみのり",
        "うずしお",
        "ダイビング"
      ]
    },
    {
      "tag": "charge_1_turn_normal",
      "count": 3,
      "samples": [
        "ソーラービーム",
        "ゴッドバード",
        "ソーラーブレード"
      ]
    },
    {
      "tag": "down_opp_speed_2",
      "count": 3,
      "samples": [
        "いとをはく",
        "わたほうし",
        "こわいかお"
      ]
    },
    {
      "tag": "power_half_if_grass_field",
      "count": 3,
      "samples": [
        "じしん",
        "じならし",
        "グラスフィールド"
      ]
    },
    {
      "tag": "inflict_badly_poison",
      "count": 3,
      "samples": [
        "どくどく",
        "どくどくのキバ",
        "どくびし"
      ]
    },
    {
      "tag": "up_self_speed_2",
      "count": 3,
      "samples": [
        "こうそくいどう",
        "ロックカット",
        "からをやぶる"
      ]
    },
    {
      "tag": "faint_self",
      "count": 3,
      "samples": [
        "じばく",
        "だいばくはつ",
        "ミストバースト"
      ]
    },
    {
      "tag": "recoil_if_miss",
      "count": 3,
      "samples": [
        "とびひざげり",
        "かかとおとし",
        "サンダーダイブ"
      ]
    },
    {
      "tag": "self_damage_on_fail",
      "count": 3,
      "samples": [
        "とびひざげり",
        "かかとおとし",
        "サンダーダイブ"
      ]
    },
    {
      "tag": "down_opp_accuracy_1",
      "count": 3,
      "samples": [
        "どろかけ",
        "だくりゅう",
        "ナイトバースト"
      ]
    },
    {
      "tag": "down_opp_attack_2",
      "count": 3,
      "samples": [
        "あまえる",
        "おきみやげ",
        "フェザーダンス"
      ]
    },
    {
      "tag": "up_target_attack_2",
      "count": 3,
      "samples": [
        "いばる",
        "デコレーション",
        "ハバネロエキス"
      ]
    },
    {
      "tag": "heal_self_by_weather",
      "count": 3,
      "samples": [
        "あさのひざし",
        "こうごうせい",
        "つきのひかり"
      ]
    },
    {
      "tag": "power_by_stockpile",
      "count": 3,
      "samples": [
        "たくわえる",
        "はきだす",
        "のみこむ"
      ]
    },
    {
      "tag": "heal_by_stockpile",
      "count": 3,
      "samples": [
        "たくわえる",
        "はきだす",
        "のみこむ"
      ]
    },
    {
      "tag": "copy_target_ability",
      "count": 3,
      "samples": [
        "なりきり",
        "スキルスワップ",
        "なかまづくり"
      ]
    },
    {
      "tag": "set_aurora_veil",
      "count": 3,
      "samples": [
        "かわらわり",
        "サイコファング",
        "レイジングブル"
      ]
    },
    {
      "tag": "remove_screens",
      "count": 3,
      "samples": [
        "かわらわり",
        "サイコファング",
        "レイジングブル"
      ]
    },
    {
      "tag": "down_self_special_attack_2_after",
      "count": 3,
      "samples": [
        "オーバーヒート",
        "りゅうせいぐん",
        "リーフストーム"
      ]
    },
    {
      "tag": "down_self_special_attack_2",
      "count": 3,
      "samples": [
        "オーバーヒート",
        "りゅうせいぐん",
        "リーフストーム"
      ]
    },
    {
      "tag": "down_self_defense_after",
      "count": 3,
      "samples": [
        "インファイト",
        "ぶちかまし",
        "アーマーキャノン"
      ]
    },
    {
      "tag": "swap_self_defense_special_defense",
      "count": 3,
      "samples": [
        "ガードスワップ",
        "ガードシェア",
        "ワンダールーム"
      ]
    },
    {
      "tag": "always_crit",
      "count": 3,
      "samples": [
        "やまあらし",
        "こおりのいぶき",
        "トリックフラワー"
      ]
    },
    {
      "tag": "up_self_attack_2",
      "count": 2,
      "samples": [
        "つるぎのまい",
        "からをやぶる"
      ]
    },
    {
      "tag": "disable_target_move",
      "count": 2,
      "samples": [
        "かなしばり",
        "いちゃもん"
      ]
    },
    {
      "tag": "power_by_target_weight",
      "count": 2,
      "samples": [
        "けたぐり",
        "くさむすび"
      ]
    },
    {
      "tag": "priority_down_5",
      "count": 2,
      "samples": [
        "カウンター",
        "ミラーコート"
      ]
    },
    {
      "tag": "fixed_damage",
      "count": 2,
      "samples": [
        "ちきゅうなげ",
        "ナイトヘッド"
      ]
    },
    {
      "tag": "skip_charge_if_weather",
      "count": 2,
      "samples": [
        "ソーラービーム",
        "ソーラーブレード"
      ]
    },
    {
      "tag": "power_half_if_weather",
      "count": 2,
      "samples": [
        "ソーラービーム",
        "ソーラーブレード"
      ]
    },
    {
      "tag": "power_x2_if_target_digging",
      "count": 2,
      "samples": [
        "じしん",
        "あなをほる"
      ]
    },
    {
      "tag": "down_opp_defense_2",
      "count": 2,
      "samples": [
        "いやなおと",
        "ハバネロエキス"
      ]
    },
    {
      "tag": "up_self_evasion_1",
      "count": 2,
      "samples": [
        "かげぶんしん",
        "ちいさくなる"
      ]
    },
    {
      "tag": "set_screen",
      "count": 2,
      "samples": [
        "ひかりのかべ",
        "オーロラベール"
      ]
    },
    {
      "tag": "reset_stat_stages",
      "count": 2,
      "samples": [
        "くろいきり",
        "クリアスモッグ"
      ]
    },
    {
      "tag": "inflict_random_status",
      "count": 2,
      "samples": [
        "トライアタック",
        "フェイタルクロー"
      ]
    },
    {
      "tag": "set_substitute",
      "count": 2,
      "samples": [
        "みがわり",
        "しっぽきり"
      ]
    },
    {
      "tag": "steal_item",
      "count": 2,
      "samples": [
        "どろぼう",
        "ほしがる"
      ]
    },
    {
      "tag": "power_up_if_self_hp_low",
      "count": 2,
      "samples": [
        "じたばた",
        "きしかいせい"
      ]
    },
    {
      "tag": "reduce_target_pp",
      "count": 2,
      "samples": [
        "うらみ",
        "ぶきみなじゅもん"
      ]
    },
    {
      "tag": "set_spikes",
      "count": 2,
      "samples": [
        "まきびし",
        "ひけん・ちえなみ"
      ]
    },
    {
      "tag": "needs_review_atk_via_buff",
      "count": 2,
      "samples": [
        "いばる",
        "ハバネロエキス"
      ]
    },
    {
      "tag": "power_only_first_turn",
      "count": 2,
      "samples": [
        "ねこだまし",
        "であいがしら"
      ]
    },
    {
      "tag": "down_opp_special_attack_2",
      "count": 2,
      "samples": [
        "おきみやげ",
        "かいでんぱ"
      ]
    },
    {
      "tag": "priority_down_3",
      "count": 2,
      "samples": [
        "きあいパンチ",
        "くちばしキャノン"
      ]
    },
    {
      "tag": "redirect_attacks",
      "count": 2,
      "samples": [
        "このゆびとまれ",
        "いかりのこな"
      ]
    },
    {
      "tag": "swap_item",
      "count": 2,
      "samples": [
        "トリック",
        "すりかえ"
      ]
    },
    {
      "tag": "heal_each_turn",
      "count": 2,
      "samples": [
        "ねをはる",
        "アクアリング"
      ]
    },
    {
      "tag": "remove_target_item",
      "count": 2,
      "samples": [
        "はたきおとす",
        "ふしょくガス"
      ]
    },
    {
      "tag": "power_up_if_self_hp_high",
      "count": 2,
      "samples": [
        "ふんか",
        "しおふき"
      ]
    },
    {
      "tag": "up_ally_attack_1",
      "count": 2,
      "samples": [
        "とおぼえ",
        "コーチング"
      ]
    },
    {
      "tag": "change_self_type",
      "count": 2,
      "samples": [
        "はねやすめ",
        "もえつきる"
      ]
    },
    {
      "tag": "down_self_speed_1",
      "count": 2,
      "samples": [
        "アームハンマー",
        "アイスハンマー"
      ]
    },
    {
      "tag": "eat_or_steal_berry",
      "count": 2,
      "samples": [
        "ついばむ",
        "むしくい"
      ]
    },
    {
      "tag": "counter_damage_x1_5",
      "count": 2,
      "samples": [
        "メタルバースト",
        "ほうふく"
      ]
    },
    {
      "tag": "copy_last_move",
      "count": 2,
      "samples": [
        "まねっこ",
        "さいはい"
      ]
    },
    {
      "tag": "swap_self_attack_special_attack",
      "count": 2,
      "samples": [
        "パワースワップ",
        "パワーシェア"
      ]
    },
    {
      "tag": "up_self_special_attack_2",
      "count": 2,
      "samples": [
        "わるだくみ",
        "からをやぶる"
      ]
    },
    {
      "tag": "set_stealth_rock",
      "count": 2,
      "samples": [
        "ステルスロック",
        "がんせきアックス"
      ]
    },
    {
      "tag": "recoil_1_2",
      "count": 2,
      "samples": [
        "もろはのずつき",
        "はめつのひかり"
      ]
    },
    {
      "tag": "power_by_weight_difference",
      "count": 2,
      "samples": [
        "ヘビーボンバー",
        "ヒートスタンプ"
      ]
    },
    {
      "tag": "power_up_by_self_boosts",
      "count": 2,
      "samples": [
        "アシストパワー",
        "つけあがる"
      ]
    },
    {
      "tag": "cure_target_freeze",
      "count": 2,
      "samples": [
        "ねっとう",
        "シャカシャカほう"
      ]
    },
    {
      "tag": "ignore_target_stat_stages",
      "count": 2,
      "samples": [
        "せいなるつるぎ",
        "DDラリアット"
      ]
    },
    {
      "tag": "power_x2_if_prev_turn_failed",
      "count": 2,
      "samples": [
        "じだんだ",
        "やけっぱち"
      ]
    },
    {
      "tag": "remove_field",
      "count": 2,
      "samples": [
        "アイアンローラー",
        "アイススピナー"
      ]
    },
    {
      "tag": "charge_1_turn_with_stat_up",
      "count": 2,
      "samples": [
        "メテオビーム",
        "エレクトロビーム"
      ]
    },
    {
      "tag": "power_x2_if_self_debuffed",
      "count": 2,
      "samples": [
        "うっぷんばらし",
        "やけっぱち"
      ]
    },
    {
      "tag": "drain_each_turn",
      "count": 1,
      "samples": [
        "やどりぎのタネ"
      ]
    },
    {
      "tag": "up_self_special_defense_2",
      "count": 1,
      "samples": [
        "ドわすれ"
      ]
    },
    {
      "tag": "halve_target_hp",
      "count": 1,
      "samples": [
        "いかりのまえば"
      ]
    },
    {
      "tag": "cure_status",
      "count": 1,
      "samples": [
        "いやしのすず"
      ]
    },
    {
      "tag": "set_mist",
      "count": 1,
      "samples": [
        "しんぴのまもり"
      ]
    },
    {
      "tag": "delayed_attack",
      "count": 1,
      "samples": [
        "みらいよち"
      ]
    },
    {
      "tag": "down_self_attack_1",
      "count": 1,
      "samples": [
        "ばかぢから"
      ]
    },
    {
      "tag": "power_x2_if_weather",
      "count": 1,
      "samples": [
        "ウェザーボール"
      ]
    },
    {
      "tag": "no_effect_on_ice",
      "count": 1,
      "samples": [
        "ぜったいれいど"
      ]
    },
    {
      "tag": "heal_switch_in",
      "count": 1,
      "samples": [
        "いやしのねがい"
      ]
    },
    {
      "tag": "set_tailwind",
      "count": 1,
      "samples": [
        "おいかぜ"
      ]
    },
    {
      "tag": "up_self_random_stat_2",
      "count": 1,
      "samples": [
        "つぼをつく"
      ]
    },
    {
      "tag": "set_toxic_spikes",
      "count": 1,
      "samples": [
        "どくびし"
      ]
    },
    {
      "tag": "set_self_floating",
      "count": 1,
      "samples": [
        "でんじふゆう"
      ]
    },
    {
      "tag": "down_opp_evasion_1",
      "count": 1,
      "samples": [
        "きりばらい"
      ]
    },
    {
      "tag": "use_defense_for_speed",
      "count": 1,
      "samples": [
        "サイコショック"
      ]
    },
    {
      "tag": "use_target_attack",
      "count": 1,
      "samples": [
        "イカサマ"
      ]
    },
    {
      "tag": "recoil_1_4",
      "count": 1,
      "samples": [
        "ワイルドボルト"
      ]
    },
    {
      "tag": "set_field_grass",
      "count": 1,
      "samples": [
        "グラスフィールド"
      ]
    },
    {
      "tag": "set_field_misty",
      "count": 1,
      "samples": [
        "ミストフィールド"
      ]
    },
    {
      "tag": "set_sticky_web",
      "count": 1,
      "samples": [
        "ねばねばネット"
      ]
    },
    {
      "tag": "set_field_electric",
      "count": 1,
      "samples": [
        "エレキフィールド"
      ]
    },
    {
      "tag": "set_field_psychic",
      "count": 1,
      "samples": [
        "サイコフィールド"
      ]
    },
    {
      "tag": "use_defense_for_damage",
      "count": 1,
      "samples": [
        "ボディプレス"
      ]
    },
    {
      "tag": "auto_physical_or_special",
      "count": 1,
      "samples": [
        "シェルアームズ"
      ]
    },
    {
      "tag": "power_x2_if_field",
      "count": 1,
      "samples": [
        "だいちのはどう"
      ]
    },
    {
      "tag": "inflict_burn_if_target_boosted",
      "count": 1,
      "samples": [
        "しっとのほのお"
      ]
    },
    {
      "tag": "power_up_if_target_hp_high",
      "count": 1,
      "samples": [
        "ハードプレス"
      ]
    },
    {
      "tag": "inflict_confuse_if_target_boosted",
      "count": 1,
      "samples": [
        "みわくのボイス"
      ]
    }
  ],
  "flags": [
    {
      "flag": "sound",
      "count": 24,
      "samples": [
        "ほえる",
        "うたう",
        "いやなおと",
        "いびき",
        "ほろびのうた"
      ]
    },
    {
      "flag": "punch",
      "count": 14,
      "samples": [
        "ほのおのパンチ",
        "れいとうパンチ",
        "かみなりパンチ",
        "マッハパンチ",
        "ばくれつパンチ"
      ]
    },
    {
      "flag": "charge",
      "count": 10,
      "samples": [
        "そらをとぶ",
        "ソーラービーム",
        "あなをほる",
        "ゴッドバード",
        "ダイビング"
      ]
    },
    {
      "flag": "ball",
      "count": 10,
      "samples": [
        "ヘドロばくだん",
        "でんじほう",
        "シャドーボール",
        "ウェザーボール",
        "タネマシンガン"
      ]
    },
    {
      "flag": "recharge",
      "count": 6,
      "samples": [
        "はかいこうせん",
        "ブラストバーン",
        "ハイドロカノン",
        "ハードプラント",
        "ギガインパクト"
      ]
    },
    {
      "flag": "pulse",
      "count": 6,
      "samples": [
        "みずのはどう",
        "はどうだん",
        "あくのはどう",
        "りゅうのはどう",
        "いやしのはどう"
      ]
    },
    {
      "flag": "change_item",
      "count": 5,
      "samples": [
        "どろぼう",
        "トリック",
        "リサイクル",
        "はたきおとす",
        "ほしがる"
      ]
    },
    {
      "flag": "change_type",
      "count": 5,
      "samples": [
        "ウェザーボール",
        "みずびたし",
        "そうでん",
        "だいちのはどう",
        "レイジングブル"
      ]
    },
    {
      "flag": "ohko",
      "count": 4,
      "samples": [
        "ハサミギロチン",
        "つのドリル",
        "じわれ",
        "ぜったいれいど"
      ]
    },
    {
      "flag": "change_ability",
      "count": 4,
      "samples": [
        "なりきり",
        "スキルスワップ",
        "シンプルビーム",
        "なかまづくり"
      ]
    }
  ],
  "effect_kinds": [
    {
      "kind": "status",
      "count": 64,
      "samples": [
        "ほのおのパンチ(やけど 10%)",
        "れいとうパンチ(こおり 10%)",
        "かみなりパンチ(まひ 10%)",
        "のしかかり(まひ 30%)",
        "あばれる(こんらん 100%)"
      ]
    },
    {
      "kind": "flinch",
      "count": 18,
      "samples": [
        "かみつく( 30%)",
        "たきのぼり( 20%)",
        "ゴッドバード( 30%)",
        "いわなだれ( 30%)",
        "いびき( 30%)"
      ]
    }
  ]
}