{"karate-chop":{"n":2,"eff":"急所に当たりやすい(急所ランク:+1)。"},"double-slap":{"n":3,"eff":"1ターンに2～5回連続で攻撃する。"},"comet-punch":{"n":4,"eff":"1ターンに2～5回連続で攻撃する。特性『てつのこぶし』の時、威力が1.2倍になる。パンチ系の技。"},"mega-punch":{"n":5,"eff":"通常攻撃。特性『てつのこぶし』の時、威力が1.2倍になる。パンチ系の技。"},"pay-day":{"n":6,"eff":"戦闘終了後にお金が(自分のレベル×攻撃回数×5)円多く手に入る。"},"scratch":{"n":10,"eff":"通常攻撃。"},"vice-grip":{"n":11,"eff":"通常攻撃。"},"razor-wind":{"n":13,"eff":"相手全体が対象。1ターン目は攻撃せずに、2ターン目で攻撃する。急所に当たりやすい(急所ランク:+1)。"},"cut":{"n":15,"eff":"通常攻撃。切る技。"},"gust":{"n":16,"eff":"相手が技『そらをとぶ』『とびはねる』『フリーフォール』を使っている時でも命中し、ダメージが2倍になる。風技。"},"wing-attack":{"n":17,"eff":"通常攻撃。"},"slam":{"n":21,"eff":"通常攻撃。"},"vine-whip":{"n":22,"eff":"通常攻撃。"},"stomp":{"n":23,"eff":"30%の確率で相手をひるませる。相手が技『ちいさくなる』を使用していると必ず命中し、威力が2倍になる。"},"double-kick":{"n":24,"eff":"1ターンに2回連続で攻撃する。"},"jump-kick":{"n":26,"eff":"攻撃が外れたり、相手の技『まもる』などで失敗すると、自分の最大HPの半分のダメージを自分が受ける。"},"rolling-kick":{"n":27,"eff":"30%の確率で相手をひるませる。"},"sand-attack":{"n":28,"eff":"相手の命中率を1段階下げる。"},"headbutt":{"n":29,"eff":"30%の確率で相手をひるませる。"},"horn-attack":{"n":30,"eff":"通常攻撃。"},"fury-attack":{"n":31,"eff":"1ターンに2～5回連続で攻撃する。"},"tackle":{"n":33,"eff":"通常攻撃。"},"take-down":{"n":36,"eff":"相手に与えたダメージの1/4を自分も受ける。"},"tail-whip":{"n":39,"eff":"相手全体が対象。相手の『ぼうぎょ』ランクを1段階下げる。"},"poison-sting":{"n":40,"eff":"30%の確率で相手を『どく』状態にする。"},"twineedle":{"n":41,"eff":"1ターンに2回連続で攻撃する。20%の確率で相手を『どく』状態にする。"},"leer":{"n":43,"eff":"相手全体が対象。相手の『ぼうぎょ』ランクを1段階下げる。"},"growl":{"n":45,"eff":"相手全体が対象。相手の『こうげき』ランクを1段階下げる。音系の技。相手の『みがわり』状態を貫通する。"},"supersonic":{"n":48,"eff":"相手を1～4ターンの間『こんらん』状態にする。音系の技。相手の『みがわり』状態を貫通する。"},"sonic-boom":{"n":49,"eff":"20の固定ダメージを与える。タイプには無効だが、それ以外のタイプ相性の影響を受けない。"},"acid":{"n":51,"eff":"相手全体が対象。10%の確率で相手の『とくぼう』ランクを1段階下げる。"},"ember":{"n":52,"eff":"10%の確率で相手を『やけど』状態にする。"},"mist":{"n":54,"eff":"5ターンの間、自分と味方のポケモンは能力ランクを下げられなくなる。交代しても効果は続く。"},"water-gun":{"n":55,"eff":"通常攻撃。"},"psybeam":{"n":60,"eff":"10%の確率で相手を1～4ターンの間『こんらん』状態にする。"},"bubble-beam":{"n":61,"eff":"10%の確率で相手の『すばやさ』ランクを1段階下げる。"},"aurora-beam":{"n":62,"eff":"10%の確率で相手の『こうげき』ランクを1段階下げる。"},"peck":{"n":64,"eff":"通常攻撃。"},"submission":{"n":66,"eff":"相手に与えたダメージの1/4を自分も受ける。"},"strength":{"n":70,"eff":"通常攻撃。"},"absorb":{"n":71,"eff":"相手に与えたダメージの半分だけ自分のHPが回復する。"},"mega-drain":{"n":72,"eff":"相手に与えたダメージの半分だけ自分のHPが回復する。"},"razor-leaf":{"n":75,"eff":"相手全体が対象。急所に当たりやすい(急所ランク:+1)。切る技。"},"dragon-rage":{"n":82,"eff":"40の固定ダメージを与える。タイプには無効だが、それ以外のタイプ相性の影響を受けない。"},"thunder-shock":{"n":84,"eff":"10%の確率で相手を『まひ』状態にする。"},"thunderbolt":{"n":85,"eff":"10%の確率で相手を『まひ』状態にする。"},"rock-throw":{"n":88,"eff":"通常攻撃。"},"confusion":{"n":93,"eff":"10%の確率で相手を1～4ターンの間『こんらん』状態にする。"},"meditate":{"n":96,"eff":"自分の『こうげき』ランクを1段階上げる。"},"rage":{"n":99,"eff":"自分を『いかり』状態にする。『いかり』状態の間、相手の技のダメージを受ける度に『こうげき』ランクが1段階上がる。別の技を使うと『いかり』状態が解除される(変化したランクはそのまま)。"},"teleport":{"n":100,"eff":"必ず後攻になる(優先度:-6)。手持ちのポケモンと入れ替わる。(第7世代までは、野生のポケモンとの戦闘を終了する効果だった)"},"mimic":{"n":102,"eff":"一時的に、相手が最後に自分に使った技が使えるようになる。PPはコピーした技のポイントアップ未使用時の最大値となる。交代すると元に戻る。"},"harden":{"n":106,"eff":"自分の『ぼうぎょ』ランクを1段階上げる。"},"smokescreen":{"n":108,"eff":"相手の命中率を1段階下げる。"},"withdraw":{"n":110,"eff":"自分の『ぼうぎょ』ランクを1段階上げる。"},"defense-curl":{"n":111,"eff":"自分の『ぼうぎょ』ランクを1段階上げる。"},"barrier":{"n":112,"eff":"自分の『ぼうぎょ』ランクを2段階上げる。"},"bide":{"n":117,"eff":"必ず先制できる(優先度:+1)。今後2ターンの間に受けたダメージの2倍を相手に与える。その間、全く行動できなくなる。タイプには無効だが、それ以外のタイプ相性の影響を受けない。"},"metronome":{"n":118,"eff":"ほぼすべての技の中からランダムで1つ使う。"},"mirror-move":{"n":119,"eff":"相手が最後に使った技で、相手を攻撃する。"},"egg-bomb":{"n":121,"eff":"通常攻撃。弾技。"},"lick":{"n":122,"eff":"30%の確率で相手を『まひ』状態にする。"},"smog":{"n":123,"eff":"40%の確率で相手を『どく』状態にする。"},"sludge":{"n":124,"eff":"30%の確率で相手を『どく』状態にする。"},"bone-club":{"n":125,"eff":"10%の確率で相手をひるませる。"},"clamp":{"n":128,"eff":"4～5ターンの間、毎ターン終了後最大HPの1/8のダメージを与え、その間タイプではない相手は逃げたり交代できない。"},"swift":{"n":129,"eff":"相手全体が対象。自分の命中率、相手の回避率に関係なく必ず命中する。"},"skull-bash":{"n":130,"eff":"1ターン目に100%の確率で自分の『ぼうぎょ』ランクを1段階上げ、2ターン目で攻撃する。"},"spike-cannon":{"n":131,"eff":"1ターンに2～5回連続で攻撃する。"},"constrict":{"n":132,"eff":"10%の確率で相手の『すばやさ』ランクを1段階下げる。"},"kinesis":{"n":134,"eff":"相手の命中率を1段階下げる。"},"soft-boiled":{"n":135,"eff":"HPが最大HPの半分回復する。"},"dream-eater":{"n":138,"eff":"相手に与えたダメージの半分だけ自分のHPが回復する。相手が『ねむり』状態の時だけ成功する。"},"poison-gas":{"n":139,"eff":"相手全体が対象。相手を『どく』状態にする。タイプやタイプには無効。"},"barrage":{"n":140,"eff":"1ターンに2～5回連続で攻撃する。弾技。"},"lovely-kiss":{"n":142,"eff":"相手を2～4ターン(実質1～3ターン)の間『ねむり』状態にする。"},"bubble":{"n":145,"eff":"相手全体が対象。10%の確率で相手の『すばやさ』ランクを1段階下げる。"},"dizzy-punch":{"n":146,"eff":"20%の確率で相手を1～4ターンの間『こんらん』状態にする。特性『てつのこぶし』の時、威力が1.2倍になる。パンチ系の技。"},"spore":{"n":147,"eff":"相手を2～4ターン(実質1～3ターン)の間『ねむり』状態にする。タイプや特性『ぼうじん』、道具『ぼうじんゴーグル』を持っているポケモンには無効。"},"flash":{"n":148,"eff":"相手の命中率を1段階下げる。"},"psywave":{"n":149,"eff":"ランダムに(自分のレベル×0.5～1.5)が相手に与えるダメージになる。タイプには無効だが、それ以外のタイプ相性の影響を受けない。"},"splash":{"n":150,"eff":"何も起こらない。"},"fury-swipes":{"n":154,"eff":"1ターンに2～5回連続で攻撃する。"},"bonemerang":{"n":155,"eff":"1ターンに2回連続で攻撃する。"},"hyper-fang":{"n":158,"eff":"10%の確率で相手をひるませる。噛み技。"},"sharpen":{"n":159,"eff":"自分の『こうげき』ランクを1段階上げる。"},"conversion":{"n":160,"eff":"自分の『タイプ』を、自分の一番上の技と同じタイプに変える。"},"slash":{"n":163,"eff":"急所に当たりやすい(急所ランク:+1)。切る技。"},"struggle":{"n":165,"eff":"すべての技のPPが0になる等して使える技がなくなると使える。自分の最大HPの1/4を自分も受ける。『タイプ』に関係なくダメージを与える。"},"sketch":{"n":166,"eff":"この技を忘れて、相手が最後に使った技を覚える。戦闘終了後も元に戻らない。(通信対戦などでは元に戻る)"},"triple-kick":{"n":167,"eff":"1ターンに外れるまで最大3回連続で攻撃する。攻撃が当たる度に威力が10ずつ増える。"},"spider-web":{"n":169,"eff":"タイプではない相手は逃げたり、交代できなくなる。自分が場を離れると効果は消える。"},"mind-reader":{"n":170,"eff":"次のターン、使った相手に自分の技が必ず命中する。"},"nightmare":{"n":171,"eff":"相手が『ねむり』状態の時、『あくむ』状態にする。『あくむ』状態になると、毎ターン、HPが最大HPの1/4ずつ減る。ただし『ねむり』状態から覚めると『あくむ』状態も解かれる。"},"flame-wheel":{"n":172,"eff":"10%の確率で相手を『やけど』状態にする。自分が『こおり』状態の時でも使う事ができ、使うと『こおり』状態が治る。"},"conversion-2":{"n":176,"eff":"自分の『タイプ』を相手が最後に使った技が効きづらいタイプに変える。どのタイプになるかはランダム。"},"aeroblast":{"n":177,"eff":"急所に当たりやすい(急所ランク:+1)。風技。"},"powder-snow":{"n":181,"eff":"相手全体が対象。10%の確率で相手を『こおり』状態にする。"},"feint-attack":{"n":185,"eff":"自分の命中率、相手の回避率に関係なく必ず命中する。"},"octazooka":{"n":190,"eff":"50%の確率で相手の命中率を1段階下げる。弾技。"},"foresight":{"n":193,"eff":"使用後、相手の回避率に関係なく攻撃が当たる。相手がタイプの時、タイプの技が当たるようになる。"},"rollout":{"n":205,"eff":"外れるまで5ターン連続で攻撃し、攻撃が当たる度に威力が倍増する(最大480)。事前に技『まるくなる』を使っていると威力が2倍になる。"},"false-swipe":{"n":206,"eff":"この技のダメージで相手のHPが0になる時、相手のHPを1にする。野生のポケモンを捕まえる時に便利。"},"milk-drink":{"n":208,"eff":"HPが最大HPの半分回復する。"},"spark":{"n":209,"eff":"30%の確率で相手を『まひ』状態にする。"},"fury-cutter":{"n":210,"eff":"連続で使用すると攻撃が当たる度に威力が倍増していく(最大160)。攻撃が外れたり連続で使用しないと元に戻る。切る技。"},"return":{"n":216,"eff":"ポケモンがなついているほど威力が高くなる。最大102。"},"present":{"n":217,"eff":"40%の確率で威力40、30%で威力80、10%の確率で威力120になり、20%の確率で相手のHPを最大HPの1/4回復する。"},"frustration":{"n":218,"eff":"ポケモンがなついていないほど威力が高くなる。最大102。"},"sacred-fire":{"n":221,"eff":"50%の確率で相手を『やけど』状態にする。自分が『こおり』状態の時でも使う事ができ、使うと『こおり』状態が治る。"},"magnitude":{"n":222,"eff":"自分以外全員が対象。威力は5%の確率で10、10%の確率で30、20%の確率で50、30%の確率で70、20%の確率で90、10%の確率で110、5%の確率で150になる。相手が技『あなをほる』を使っている時でも命中し、ダメージが2倍になる。"},"dragon-breath":{"n":225,"eff":"30%の確率で相手を『まひ』状態にする。"},"pursuit":{"n":228,"eff":"相手がポケモンを交代する時に攻撃すると、交代前のポケモンに2倍のダメージを与える。"},"metal-claw":{"n":232,"eff":"10%の確率で自分の『こうげき』ランクが1段階上がる。"},"vital-throw":{"n":233,"eff":"必ず後攻になるが(優先度:-1)、自分の命中率、相手の回避率に関係なく必ず命中する。"},"hidden-power":{"n":237,"eff":"自分の個体値によって『タイプ』が変わる。(BW2までは威力も個体値によって変化)"},"twister":{"n":239,"eff":"相手全体が対象。20%の確率で相手をひるませる。相手が技『そらをとぶ』『とびはねる』『フリーフォール』を使っている時でも命中し、ダメージが2倍になる。風技。"},"rock-smash":{"n":249,"eff":"50%の確率で相手の『ぼうぎょ』ランクを1段階下げる。"},"hail":{"n":258,"eff":"5ターンの間、天気を『あられ』にする。タイプではないポケモンは、毎ターン最大HPの1/16のダメージを受ける。"},"smelling-salts":{"n":265,"eff":"相手が『まひ』状態の時、ダメージが2倍になるが、『まひ』状態は治る。"},"nature-power":{"n":267,"eff":"地形によって出る技が変わる。それ以外は『トライアタック』となる。"},"assist":{"n":274,"eff":"自分以外の『てもち』のポケモンの技のうち1つをランダムで使う。PPが減少するのはこの技のみ。"},"magic-coat":{"n":277,"eff":"必ず先制でき、そのターンの間、自分が受ける変化技を使用した相手に跳ね返す。(優先度:+4)"},"revenge":{"n":279,"eff":"そのターンに相手の技のダメージを受けると威力が2倍になる。必ず後攻になる(優先度:-4)。"},"refresh":{"n":287,"eff":"『どく』『まひ』『やけど』状態が治る。"},"grudge":{"n":288,"eff":"相手の技のダメージで『ひんし』状態になった場合、その技のPPを0にする。"},"snatch":{"n":289,"eff":"必ず先制でき(優先度:+4)、相手が使おうとした、能力ランクを変化させる技や回復系の技の効果を奪い、自分にかける。"},"secret-power":{"n":290,"eff":"30%の確率で相手に追加効果を与える。追加効果は地形によって変わる。その他は『まひ』状態にする。"},"arm-thrust":{"n":292,"eff":"1ターンに2～5回連続で攻撃する。"},"camouflage":{"n":293,"eff":"自分の『タイプ』を地形によって変える。ただし、同じ『タイプ』を持っている場合は失敗する。"},"tail-glow":{"n":294,"eff":"自分の『とくこう』ランクが3段階上がる。"},"luster-purge":{"n":295,"eff":"50%の確率で相手の『とくぼう』ランクを1段階下げる。"},"mist-ball":{"n":296,"eff":"50%の確率で相手の『とくこう』ランクを1段階下げる。弾技。"},"mud-sport":{"n":300,"eff":"5ターンの間、タイプの技の威力が1/3になる。"},"ice-ball":{"n":301,"eff":"外れるまで5ターン連続で攻撃し、攻撃が当たる度にダメージが倍増する。事前に技『まるくなる』を使っているとダメージが2倍になる。弾技。"},"needle-arm":{"n":302,"eff":"30%の確率で相手をひるませる。"},"astonish":{"n":310,"eff":"30%の確率で相手をひるませる。"},"aromatherapy":{"n":312,"eff":"自分と味方全体のポケモンの状態異常を治す。この技は『ダイウォール』の効果も受けない。"},"odor-sleuth":{"n":316,"eff":"使用後、相手の回避率に関係なく攻撃が当たる。相手がタイプの時、タイプの技が当たるようになる。"},"silver-wind":{"n":318,"eff":"10%の確率で自分の『こうげき』『ぼうぎょ』『とくこう』『とくぼう』『すばやさ』ランクが1段階ずつ上がる。"},"grass-whistle":{"n":320,"eff":"音系の技。相手を2～4ターン(実質1～3ターン)の間『ねむり』状態にする。"},"signal-beam":{"n":324,"eff":"10%の確率で相手を1～4ターンの間『こんらん』状態にする。"},"sky-uppercut":{"n":327,"eff":"相手が技『そらをとぶ』『とびはねる』『フリーフォール』を使っている時でも命中する。特性『てつのこぶし』の時、威力が1.2倍になる。パンチ系の技。"},"poison-tail":{"n":342,"eff":"10%の確率で相手を『どく』状態にする。急所に当たりやすい(急所ランク:+1)。"},"magical-leaf":{"n":345,"eff":"自分の命中率、相手の回避率に関係なく必ず命中する。"},"water-sport":{"n":346,"eff":"5ターンの間、タイプの技の威力が1/3になる。"},"shock-wave":{"n":351,"eff":"自分の命中率、相手の回避率に関係なく必ず命中する。"},"doom-desire":{"n":353,"eff":"2ターン後に攻撃する。交代した場合は同じ位置にいるポケモンに攻撃する。タイプ相性の影響を受ける。"},"psycho-boost":{"n":354,"eff":"攻撃後、100%の確率で自分の『とくこう』ランクが2段階下がる。"},"miracle-eye":{"n":357,"eff":"使用後、相手の回避率に関係なく攻撃が当たる。相手がタイプの時、タイプの技が当たるようになる。"},"wake-up-slap":{"n":358,"eff":"相手が『ねむり』状態の時、ダメージが2倍になるが、『ねむり』状態は治る。"},"brine":{"n":362,"eff":"相手のHPが最大HPの半分以下の時、威力が2倍になる。"},"natural-gift":{"n":363,"eff":"持っている『きのみ』によって『タイプ』と威力が変わる。『きのみ』はなくなる。"},"embargo":{"n":373,"eff":"5ターンの間、持っている道具を使えなくなる。トレーナーもそのポケモンには道具を使えない。"},"psycho-shift":{"n":375,"eff":"自分の状態異常を相手に移し、自分は回復する。"},"trump-card":{"n":376,"eff":"自分の命中率、相手の回避率に関係なく必ず命中する。この技の残りPPが少ない時ほど威力が高くなる。"},"heal-block":{"n":377,"eff":"相手全体が対象。5ターンの間、相手は回復系の技が使えなくなり、また特性や道具、場の状態などでHPが回復しなくなる。"},"wring-out":{"n":378,"eff":"相手の残りHPが多いほど威力が高くなる。(120×相手の残りHP÷相手の最大HP)が威力になる。"},"lucky-chant":{"n":381,"eff":"5ターンの間、相手の攻撃が急所に当たらなくなる。"},"me-first":{"n":382,"eff":"相手が使おうとしている攻撃技を自分の技として使い、ダメージを1.5倍にする。後攻になった場合や、相手の技が変化技の場合は失敗する。"},"punishment":{"n":386,"eff":"威力は60を基本として、相手のいずれかの能力ランクが1つ上がる度に20上がる。(最大200)"},"heart-swap":{"n":391,"eff":"自分と相手のすべての能力ランクを入れ替える。"},"force-palm":{"n":395,"eff":"30%の確率で相手を『まひ』状態にする。"},"mud-bomb":{"n":426,"eff":"30%の確率で相手の命中率を1段階下げる。弾技。"},"mirror-shot":{"n":429,"eff":"30%の確率で相手の命中率を1段階下げる。"},"rock-climb":{"n":431,"eff":"20%の確率で相手を1～4ターンの間『こんらん』状態にする。"},"magnet-bomb":{"n":443,"eff":"自分の命中率、相手の回避率に関係なく必ず命中する。弾技。"},"captivate":{"n":445,"eff":"相手全体が対象。相手が自分とは異なる性別の場合、相手の『とくこう』を2段階下げる。自分と相手の性別が同じ時や、どちらかが性別不明の場合は失敗する。"},"chatter":{"n":448,"eff":"『ペラップ』が使うと、100%の確率で相手を『こんらん』状態にする。音系の技。相手の『みがわり』状態を貫通する。"},"judgment":{"n":449,"eff":"持たせた『プレート』によって『タイプ』が変わる。"},"attack-order":{"n":454,"eff":"急所に当たりやすい(急所ランク:+1)。"},"defend-order":{"n":455,"eff":"自分の『ぼうぎょ』『とくぼう』ランクが1段階ずつ上がる。"},"heal-order":{"n":456,"eff":"HPが最大HPの半分回復する。"},"roar-of-time":{"n":459,"eff":"使用した次のターンは行動できない。"},"spacial-rend":{"n":460,"eff":"急所に当たりやすい(急所ランク:+1)。"},"lunar-dance":{"n":461,"eff":"自分が『ひんし』になる代わりに、次に出す自分のポケモンの状態異常とHPとPPが全回復する。踊り系の技。"},"crush-grip":{"n":462,"eff":"相手の残りHPが多いほど威力が高くなる。(120×相手の残りHP÷相手の最大HP)が威力になる。"},"magma-storm":{"n":463,"eff":"4～5ターンの間、毎ターン終了後最大HPの1/8のダメージを与え、その間タイプではない相手は逃げたり交代できない。"},"dark-void":{"n":464,"eff":"相手全体が対象。相手を2～4ターン(実質1～3ターン)の間『ねむり』状態にする。『ダークライ』以外のポケモンが使うと失敗する。"},"seed-flare":{"n":465,"eff":"40%の確率で相手の『とくぼう』ランクを2段階下げる。"},"ominous-wind":{"n":466,"eff":"10%の確率で自分の『こうげき』『ぼうぎょ』『とくこう』『とくぼう』『すばやさ』ランクが1段階ずつ上がる。"},"shadow-force":{"n":467,"eff":"1ターン目に消えて、2ターン目に攻撃する。消えている間はほとんどの技を受けない。相手の『まもる』『みきり』などの効果を受けない(『ダイウォール』を除く)。"},"hone-claws":{"n":468,"eff":"自分の『こうげき』『命中率』ランクが1段階ずつ上がる。"},"autotomize":{"n":475,"eff":"自分の『すばやさ』ランクが2段階上がる。また、自分の『おもさ』が100kg軽くなる。"},"telekinesis":{"n":477,"eff":"3ターンの間、相手を『テレキネシス』状態にする。タイプの技が当たらなくなるが、それ以外の技が必ず命中するようになる。ただし、一撃必殺の技は変化しない。"},"flame-burst":{"n":481,"eff":"ダブルバトルの時、相手の周りにいるポケモンにも相手の最大HPの1/16のダメージを与える。"},"synchronoise":{"n":485,"eff":"自分以外全員が対象。自分と同じ『タイプ』のポケモン全員にダメージを与える。"},"echoed-voice":{"n":497,"eff":"毎ターン、誰かが技『エコーボイス』を使う度に威力が高くなっていく。音系の技。相手の『みがわり』状態を貫通する。"},"chip-away":{"n":498,"eff":"相手の能力ランクの変化に関係なく、ダメージを与える。"},"sky-drop":{"n":507,"eff":"1ターン目に相手とともに空中へ飛び上がり、2ターン目で攻撃する。空中にいる間は一部の技以外を受けず、相手は行動できない。タイプのポケモンはダメージを受けない。相手が体重200kg以上の場合は失敗する。"},"shift-gear":{"n":508,"eff":"自分の『すばやさ』ランクが2段階、『こうげき』ランクが1段階上がる。"},"incinerate":{"n":510,"eff":"相手全体が対象。相手の持っている『きのみ』や『ノーマルジュエル』を使えなくする。"},"retaliate":{"n":514,"eff":"前のターンに味方のポケモンが倒されていると威力が2倍になる。"},"bestow":{"n":516,"eff":"自分の持っている道具を相手に渡す。相手が道具を持っている時は失敗する。"},"water-pledge":{"n":518,"eff":"ダブルバトルで他の『ちかい』技と組み合わせると追加効果が出る。また、威力が150になる。"},"fire-pledge":{"n":519,"eff":"ダブルバトルで他の『ちかい』技と組み合わせると追加効果が出る。また、威力が150になる。"},"grass-pledge":{"n":520,"eff":"ダブルバトルで他の『ちかい』技と組み合わせると追加効果が出る。また、威力が150になる。"},"work-up":{"n":526,"eff":"自分の『こうげき』『とくこう』ランクが1段階ずつ上がる。"},"dual-chop":{"n":530,"eff":"1ターンに2回連続で攻撃する。"},"heart-stamp":{"n":531,"eff":"30%の確率で相手をひるませる。"},"leaf-tornado":{"n":536,"eff":"50%の確率で相手の命中率を1段階下げる。"},"steamroller":{"n":537,"eff":"30%の確率で相手をひるませる。相手が技『ちいさくなる』を使用していると威力が2倍になる。"},"psystrike":{"n":540,"eff":"相手の『とくぼう』ではなく、相手の『ぼうぎょ』の能力値でダメージ計算する。"},"head-charge":{"n":543,"eff":"相手に与えたダメージの1/4を自分も受ける。"},"gear-grind":{"n":544,"eff":"1ターンに2回連続で攻撃する。"},"searing-shot":{"n":545,"eff":"自分以外全員が対象。30%の確率で相手を『やけど』状態にする。弾技。"},"techno-blast":{"n":546,"eff":"持たせた『カセット』によって『タイプ』が変わる。"},"relic-song":{"n":547,"eff":"相手全体が対象。それぞれ10%の確率で相手を2～4ターン(実質1～3ターン)の間『ねむり』状態にする。音系の技。相手の『みがわり』状態を貫通する。"},"secret-sword":{"n":548,"eff":"相手の『とくぼう』ではなく、相手の『ぼうぎょ』の能力値でダメージ計算する。切る技。"},"glaciate":{"n":549,"eff":"相手全体が対象。100%の確率で相手の『すばやさ』ランクを1段階下げる。"},"bolt-strike":{"n":550,"eff":"20%の確率で相手を『まひ』状態にする。"},"blue-flare":{"n":551,"eff":"20%の確率で相手を『やけど』状態にする。"},"freeze-shock":{"n":553,"eff":"1ターン目は攻撃せずに、2ターン目で攻撃する。30%の確率で相手を『まひ』状態にする。"},"ice-burn":{"n":554,"eff":"1ターン目は攻撃せずに、2ターン目で攻撃する。30%の確率で相手を『やけど』状態にする。"},"v-create":{"n":557,"eff":"攻撃後、自分の『すばやさ』『ぼうぎょ』『とくぼう』ランクが1段階ずつ下がる。"},"fusion-flare":{"n":558,"eff":"相手・味方を問わず同じターンに技『クロスサンダー』が使われていると、威力が2倍になる。自分が『こおり』状態の時でも使う事ができ、使うと『こおり』状態が治る。"},"fusion-bolt":{"n":559,"eff":"相手・味方を問わず同じターンに技『クロスフレイム』が使われていると、威力が2倍になる。"},"play-nice":{"n":560,"eff":"相手の『こうげき』ランクを1段階下げる。自分の命中率、相手の回避率に関係なく必ず命中する。相手の『みがわり』状態を貫通する。"},"fairy-wind":{"n":561,"eff":"通常攻撃。風技。"},"disarming-voice":{"n":566,"eff":"相手全体が対象。自分の命中率、相手の回避率に関係なく必ず命中する。音系の技。相手の『みがわり』状態を貫通する。"},"power-up-punch":{"n":573,"eff":"100%の確率で自分の『こうげき』ランクが1段階上がる。特性『てつのこぶし』の時、威力が1.2倍になる。パンチ系の技。"},"confide":{"n":576,"eff":"相手の『とくこう』ランクを1段階下げる。自分の命中率、相手の回避率に関係なく必ず命中する。音系の技。相手の『みがわり』状態を貫通する。"},"crafty-shield":{"n":583,"eff":"必ず先制でき(優先度:+3)、そのターンの間、すべての味方への変化技を無効化する。なお、場を対象とした技には効果がない。"},"mat-block":{"n":589,"eff":"そのターンの間、自分と味方への攻撃技を無効化する(先制技ではない)。変化技は防げない。ただし、出た最初のターンしか成功しない。"},"geomancy":{"n":592,"eff":"1ターン目にためて、2ターン目に自分の『とくこう』『とくぼう』『すばやさ』ランクが2段階ずつ上がる。"},"oblivion-wing":{"n":593,"eff":"相手に与えたダメージの3/4だけ自分のHPが回復する。"},"powder":{"n":594,"eff":"必ず先制でき(優先度:+1)、そのターンに相手がタイプの技を使うと、相手は技が失敗し最大HPの1/4のダメージを受ける。"},"rototiller":{"n":596,"eff":"すべてのタイプのポケモンの『こうげき』『とくこう』ランクが1段階ずつ上がる。"},"ion-deluge":{"n":597,"eff":"必ず先制でき(優先度:+1)、そのターンの間、すべてのタイプの技をタイプにする。"},"venom-drench":{"n":602,"eff":"相手全体が対象。『どく』『もうどく』状態のすべての相手の『こうげき』『とくこう』『すばやさ』ランクを1段階ずつ下げる。"},"lands-wrath":{"n":606,"eff":"相手全体が対象。通常攻撃。"},"flower-shield":{"n":607,"eff":"すべてのタイプのポケモンの『ぼうぎょ』ランクが1段階上がる。"},"happy-hour":{"n":608,"eff":"戦闘後に得られる賞金が2倍になる。"},"celebrate":{"n":609,"eff":"効果なし。"},"hold-back":{"n":610,"eff":"この技のダメージで相手のHPが0になる時、相手のHPを1にする。野生のポケモンを捕まえる時に便利。"},"diamond-storm":{"n":611,"eff":"相手全体が対象。50%の確率で自分の『ぼうぎょ』ランクが2段階上がる。"},"precipice-blades":{"n":612,"eff":"相手全体が対象。通常攻撃。"},"origin-pulse":{"n":613,"eff":"相手全体が対象。通常攻撃。波動技。"},"dragon-ascent":{"n":614,"eff":"100%の確率で自分の『ぼうぎょ』『とくぼう』ランクが1段階ずつ下がる。"},"hyperspace-hole":{"n":615,"eff":"相手の『まもる』『みきり』などの効果を受けない(『ダイウォール』を除く)。相手の『みがわり』状態を貫通する。"},"hyperspace-fury":{"n":616,"eff":"相手の『まもる』『みきり』などの効果を受けない(『ダイウォール』を除く)。相手の『みがわり』状態を貫通する。攻撃後、自分の『ぼうぎょ』ランクが1段階下がる。なお、『ときはなたれしフーパ』以外のポケモンが使用した場合、失敗する。"},"steam-eruption":{"n":617,"eff":"30%の確率で相手を『やけど』状態にする。自分が『こおり』状態の時でも使う事ができ、使うと『こおり』状態が治る。また、相手の『こおり』状態を治す。"},"thousand-arrows":{"n":619,"eff":"相手全体が対象。タイプや特性『ふゆう』のポケモンにも当たり、以後は他のタイプの技も当たるようになる。また、技『そらをとぶ』『とびはねる』『でんじふゆう』『テレキネシス』の効果が解除される。"},"thousand-waves":{"n":620,"eff":"相手全体が対象。タイプではない相手は逃げたり、交代できなくなる。自分が場を離れると効果は消える。"},"leafage":{"n":621,"eff":"通常攻撃。"},"darkest-lariat":{"n":623,"eff":"相手の能力ランクの変化に関係なく、ダメージを与える。"},"revelation-dance":{"n":625,"eff":"この技の『タイプ』は、自分の『タイプ1』と同じになる。テラスタル時は、テラスタイプと同じタイプになる。踊り系の技。"},"multi-attack":{"n":630,"eff":"持たせた専用の道具『メモリ』の種類によって『タイプ』が変わる。(第7世代までは威力90)"},"shell-trap":{"n":631,"eff":"相手全体が対象。必ず後攻になる(優先度:-3)。そのターン、最初に相手の物理技のダメージを受けた直後に、相手全体を攻撃する。自分のターンまでに相手の物理技のダメージを受けなかった場合は失敗する。"},"natures-madness":{"n":633,"eff":"相手のHPを残りHPの半分にする。"},"dragon-hammer":{"n":635,"eff":"通常攻撃。"},"sunsteel-strike":{"n":636,"eff":"相手の特性の影響を受けずに攻撃する。"},"moongeist-beam":{"n":637,"eff":"相手の特性の影響を受けずに攻撃する。"},"core-enforcer":{"n":638,"eff":"相手全体が対象。この技のダメージを受けたポケモンがそのターンにすでに技を使用していた場合、そのポケモンの特性を無効にする。"},"fleur-cannon":{"n":639,"eff":"攻撃後、自分の『とくこう』ランクが2段階下がる。"},"floral-healing":{"n":645,"eff":"相手は最大HPの1/2回復する。ただし、『グラスフィールド』の時は最大HPの2/3回復する。"},"shore-up":{"n":647,"eff":"HPが最大HPの半分回復する。ただし、天気が『すなあらし』の時は最大HPの2/3回復する。"},"purify":{"n":648,"eff":"相手の状態異常を回復し、自分のHPも最大HPの1/2回復する。相手が状態異常ではない時は失敗する。"},"zing-zap":{"n":649,"eff":"30%の確率で相手をひるませる。"},"anchor-shot":{"n":650,"eff":"タイプではない相手は逃げたり、交代できなくなる。自分が場を離れると効果は消える。"},"shadow-bone":{"n":651,"eff":"20%の確率で、相手の『ぼうぎょ』ランクを1段階下げる。"},"spotlight":{"n":654,"eff":"必ず先制できる(優先度:+3)。この技を受けた相手はそのターン、強制的に他のポケモンの技の対象となる。全体技には効果がない。ダブルバトル用。"},"high-horsepower":{"n":659,"eff":"通常攻撃。"},"laser-focus":{"n":660,"eff":"次のターン、自分の技が必ず急所に当たるようになる。"},"gear-up":{"n":668,"eff":"自分と味方全体の特性『プラス』『マイナス』のポケモンの『こうげき』『とくこう』を1段階ずつ上げる。なお、『ダイウォール』は貫通しない。"},"prismatic-laser":{"n":670,"eff":"使用した次のターンは行動できない。"},"spectral-thief":{"n":671,"eff":"相手のすべての能力ランクの上昇分を0に元に戻して、その分だけ自分の能力ランクを上げ、その後に攻撃のダメージを与える。相手のランクの下降分には影響しない。相手の『みがわり』状態を貫通する。"},"breakneck-blitz--physical":{"n":672,"eff":"Z技。威力や分類は元の技で変化する。自分の命中率、相手の回避率に関係なく必ず命中する。"},"breakneck-blitz--special":{"n":672,"eff":"Z技。威力や分類は元の技で変化する。自分の命中率、相手の回避率に関係なく必ず命中する。"},"all-out-pummeling--physical":{"n":673,"eff":"Z技。威力や分類は元の技で変化する。自分の命中率、相手の回避率に関係なく必ず命中する。"},"all-out-pummeling--special":{"n":673,"eff":"Z技。威力や分類は元の技で変化する。自分の命中率、相手の回避率に関係なく必ず命中する。"},"supersonic-skystrike--physical":{"n":674,"eff":"Z技。威力や分類は元の技で変化する。自分の命中率、相手の回避率に関係なく必ず命中する。"},"supersonic-skystrike--special":{"n":674,"eff":"Z技。威力や分類は元の技で変化する。自分の命中率、相手の回避率に関係なく必ず命中する。"},"acid-downpour--physical":{"n":675,"eff":"Z技。威力や分類は元の技で変化する。自分の命中率、相手の回避率に関係なく必ず命中する。"},"acid-downpour--special":{"n":675,"eff":"Z技。威力や分類は元の技で変化する。自分の命中率、相手の回避率に関係なく必ず命中する。"},"tectonic-rage--physical":{"n":676,"eff":"Z技。威力や分類は元の技で変化する。自分の命中率、相手の回避率に関係なく必ず命中する。"},"tectonic-rage--special":{"n":676,"eff":"Z技。威力や分類は元の技で変化する。自分の命中率、相手の回避率に関係なく必ず命中する。"},"continental-crush--physical":{"n":677,"eff":"Z技。威力や分類は元の技で変化する。自分の命中率、相手の回避率に関係なく必ず命中する。"},"continental-crush--special":{"n":677,"eff":"Z技。威力や分類は元の技で変化する。自分の命中率、相手の回避率に関係なく必ず命中する。"},"savage-spin-out--physical":{"n":678,"eff":"Z技。威力や分類は元の技で変化する。自分の命中率、相手の回避率に関係なく必ず命中する。"},"savage-spin-out--special":{"n":678,"eff":"Z技。威力や分類は元の技で変化する。自分の命中率、相手の回避率に関係なく必ず命中する。"},"never-ending-nightmare--physical":{"n":679,"eff":"Z技。威力や分類は元の技で変化する。自分の命中率、相手の回避率に関係なく必ず命中する。"},"never-ending-nightmare--special":{"n":679,"eff":"Z技。威力や分類は元の技で変化する。自分の命中率、相手の回避率に関係なく必ず命中する。"},"corkscrew-crash--physical":{"n":680,"eff":"Z技。威力や分類は元の技で変化する。自分の命中率、相手の回避率に関係なく必ず命中する。"},"corkscrew-crash--special":{"n":680,"eff":"Z技。威力や分類は元の技で変化する。自分の命中率、相手の回避率に関係なく必ず命中する。"},"inferno-overdrive--physical":{"n":681,"eff":"Z技。威力や分類は元の技で変化する。自分の命中率、相手の回避率に関係なく必ず命中する。"},"inferno-overdrive--special":{"n":681,"eff":"Z技。威力や分類は元の技で変化する。自分の命中率、相手の回避率に関係なく必ず命中する。"},"hydro-vortex--physical":{"n":682,"eff":"Z技。威力や分類は元の技で変化する。自分の命中率、相手の回避率に関係なく必ず命中する。"},"hydro-vortex--special":{"n":682,"eff":"Z技。威力や分類は元の技で変化する。自分の命中率、相手の回避率に関係なく必ず命中する。"},"bloom-doom--physical":{"n":683,"eff":"Z技。威力や分類は元の技で変化する。自分の命中率、相手の回避率に関係なく必ず命中する。"},"bloom-doom--special":{"n":683,"eff":"Z技。威力や分類は元の技で変化する。自分の命中率、相手の回避率に関係なく必ず命中する。"},"gigavolt-havoc--physical":{"n":684,"eff":"Z技。威力や分類は元の技で変化する。自分の命中率、相手の回避率に関係なく必ず命中する。"},"gigavolt-havoc--special":{"n":684,"eff":"Z技。威力や分類は元の技で変化する。自分の命中率、相手の回避率に関係なく必ず命中する。"},"shattered-psyche--physical":{"n":685,"eff":"Z技。威力や分類は元の技で変化する。自分の命中率、相手の回避率に関係なく必ず命中する。"},"shattered-psyche--special":{"n":685,"eff":"Z技。威力や分類は元の技で変化する。自分の命中率、相手の回避率に関係なく必ず命中する。"},"subzero-slammer--physical":{"n":686,"eff":"Z技。威力や分類は元の技で変化する。自分の命中率、相手の回避率に関係なく必ず命中する。"},"subzero-slammer--special":{"n":686,"eff":"Z技。威力や分類は元の技で変化する。自分の命中率、相手の回避率に関係なく必ず命中する。"},"devastating-drake--physical":{"n":687,"eff":"Z技。威力や分類は元の技で変化する。自分の命中率、相手の回避率に関係なく必ず命中する。"},"devastating-drake--special":{"n":687,"eff":"Z技。威力や分類は元の技で変化する。自分の命中率、相手の回避率に関係なく必ず命中する。"},"black-hole-eclipse--physical":{"n":688,"eff":"Z技。威力や分類は元の技で変化する。自分の命中率、相手の回避率に関係なく必ず命中する。"},"black-hole-eclipse--special":{"n":688,"eff":"Z技。威力や分類は元の技で変化する。自分の命中率、相手の回避率に関係なく必ず命中する。"},"twinkle-tackle--physical":{"n":689,"eff":"Z技。威力や分類は元の技で変化する。自分の命中率、相手の回避率に関係なく必ず命中する。"},"twinkle-tackle--special":{"n":689,"eff":"Z技。威力や分類は元の技で変化する。自分の命中率、相手の回避率に関係なく必ず命中する。"},"sinister-arrow-raid":{"n":690,"eff":"『ジュナイパー』の専用Z技。自分の命中率、相手の回避率に関係なく必ず命中する。"},"malicious-moonsault":{"n":691,"eff":"『ガオガエン』の専用Z技。自分の命中率、相手の回避率に関係なく必ず命中する。相手が技『ちいさくなる』を使用していると、威力が2倍になる。"},"oceanic-operetta":{"n":692,"eff":"『アシレーヌ』の専用Z技。自分の命中率、相手の回避率に関係なく必ず命中する。"},"catastropika":{"n":693,"eff":"『ピカチュウ』の専用Z技。自分の命中率、相手の回避率に関係なく必ず命中する。"},"stoked-sparksurfer":{"n":694,"eff":"『ライチュウ(アローラの姿)』の専用Z技。100%の確率で相手を『まひ』状態にする。自分の命中率、相手の回避率に関係なく必ず命中する。"},"extreme-evoboost":{"n":695,"eff":"『イーブイ』の専用Z技。自分の『こうげき』『ぼうぎょ』『とくこう』『とくぼう』『すばやさ』が2段階ずつ上がる。"},"pulverizing-pancake":{"n":696,"eff":"『カビゴン』の専用Z技。自分の命中率、相手の回避率に関係なく必ず命中する。"},"guardian-of-alola":{"n":697,"eff":"カプ系の専用Z技。相手の残りHPの3/4のダメージを与える。自分の命中率、相手の回避率に関係なく必ず命中する。"},"genesis-supernova":{"n":698,"eff":"『ミュウ』の専用Z技。攻撃後、5ターンの間、場の状態を『サイコフィールド』にする。自分の命中率、相手の回避率に関係なく必ず命中する。"},"10-000-000-volt-thunderbolt":{"n":699,"eff":"『サトシのピカチュウ』の専用Zワザ。急所に当たりやすい(急所ランク:+2)。"},"soul-stealing-7-star-strike":{"n":700,"eff":"『マーシャドー』の専用Zワザ。"},"hold-hands":{"n":701,"eff":"効果なし。"},"mind-blown":{"n":702,"eff":"自分以外全員が対象。自分のHPを最大HPの半分だけ減らす。『まもる』などで技が防がれた場合も、HPが減る。"},"plasma-fists":{"n":703,"eff":"そのターンの間、すべてのタイプの技をタイプにする。特性『てつのこぶし』の時、威力が1.2倍になる。パンチ系の技。"},"photon-geyser":{"n":704,"eff":"自分の『こうげき』と『とくこう』の能力値の高い方でダメージ計算する。また、相手の特性の影響を受けずに攻撃する。"},"light-that-burns-the-sky":{"n":705,"eff":"『ウルトラネクロズマ』の専用Z技。自分の『こうげき』と『とくこう』の能力値の高い方でダメージ計算する。また、相手の特性の影響を受けずに攻撃する。自分の命中率、相手の回避率に関係なく必ず命中する。"},"searing-sunraze-smash":{"n":706,"eff":"『ソルガレオ』『日食ネクロズマ』の専用Z技。相手の特性の影響を受けずに攻撃する。自分の命中率、相手の回避率に関係なく必ず命中する。"},"menacing-moonraze-maelstrom":{"n":707,"eff":"『ルナアーラ』『月食ネクロズマ』の専用Z技。相手の特性の影響を受けずに攻撃する。自分の命中率、相手の回避率に関係なく必ず命中する。"},"lets-snuggle-forever":{"n":708,"eff":"『ミミッキュ』の専用Z技。自分の命中率、相手の回避率に関係なく必ず命中する。"},"splintered-stormshards":{"n":709,"eff":"『ルガルガン』の専用Z技。フィールドを解除する。自分の命中率、相手の回避率に関係なく必ず命中する。"},"clangorous-soulblaze":{"n":710,"eff":"相手全体が対象。『ジャラランガ』の専用Z技。自分の『こうげき』『ぼうぎょ』『とくこう』『とくぼう』『すばやさ』が1段階ずつ上がる。音系の技。相手の『みがわり』状態を貫通する。自分の命中率、相手の回避率に関係なく必ず命中する。"},"zippy-zap":{"n":711,"eff":"必ず先制でき(優先度:+2)、必ず急所に当たる。"},"splishy-splash":{"n":712,"eff":"相手全体が対象。30%の確率で相手を『まひ』状態にする。"},"floaty-fall":{"n":713,"eff":"30%の確率で相手をひるませる。"},"pika-papow":{"n":714,"eff":"ポケモンがなついているほど威力が高くなる。最大148。また、自分の命中率、相手の回避率に関係なく必ず命中する。"},"bouncy-bubble":{"n":715,"eff":"相手に与えたダメージの半分だけ自分のHPが回復する。"},"buzzy-buzz":{"n":716,"eff":"100%の確率で相手を『まひ』状態にする。"},"sizzly-slide":{"n":717,"eff":"100%の確率で相手を『やけど』状態にする。自分が『こおり』状態の時でも使う事ができ、使うと『こおり』状態が治る。"},"glitzy-glow":{"n":718,"eff":"味方の場に『ひかりのかべ』を作り、5ターンの間、相手の特殊攻撃のダメージを半分にする。"},"baddy-bad":{"n":719,"eff":"味方の場に『リフレクター』を作り、5ターンの間、相手の物理攻撃のダメージを半分にする。"},"sappy-seed":{"n":720,"eff":"100%の確率で相手に『やどりぎのタネ』を植え付け、毎ターン、相手のHPを最大HPの1/8ずつ減らし、その分自分のHPを回復させる。自分は交代しても効果が引き継ぐ。"},"freezy-frost":{"n":721,"eff":"すべてのポケモンの能力ランクの変化を元に戻す。"},"sparkly-swirl":{"n":722,"eff":"自分と味方全体のポケモンの状態異常を治す。"},"veevee-volley":{"n":723,"eff":"ポケモンがなついているほど威力が高くなる。最大148。また、自分の命中率、相手の回避率に関係なく必ず命中する。"},"double-iron-bash":{"n":724,"eff":"1ターンに2回連続で攻撃し、それぞれ30%の確率で相手をひるませる。特性『てつのこぶし』の時、威力が1.2倍になる。パンチ系の技。"},"max-guard":{"n":725,"eff":"必ず先制でき(優先度:+4)、そのターンの間、相手の技を受けない。連続で使うと失敗しやすくなる。『ゴーストダイブ』などの『まもる』を無視できる技やダイマックス技も防げる。ただし、『フェイント』は貫通する。"},"dynamax-cannon":{"n":726,"eff":"通常攻撃。(第8世代では相手がダイマックスしていると、ダメージが2倍になる)"},"snipe-shot":{"n":727,"eff":"急所に当たりやすい(急所ランク:+1)。特性『ひらいしん』『よびみず』や技の攻撃対象を変更する効果の影響を受けずに攻撃できる。"},"jaw-lock":{"n":728,"eff":"自分と相手のどちらかが『ひんし』になるまで、どちらも逃げたり交代できなくなる。噛み技。"},"tar-shot":{"n":731,"eff":"相手の『すばやさ』ランクを1段階下げる。また、相手の弱点にタイプを追加する。"},"octolock":{"n":735,"eff":"タイプではない相手は逃げたり、交代できなくなる。相手はその間、毎ターン『ぼうぎょ』『とくぼう』ランクが1段階ずつ下がる。ターン上限はない。"},"bolt-beak":{"n":736,"eff":"相手より先に攻撃できると技の威力が2倍になる。"},"fishious-rend":{"n":737,"eff":"相手より先に攻撃できると技の威力が2倍になる。噛み技。"},"court-change":{"n":738,"eff":"お互いの場の状態『オーロラベール』『おいかぜ』『しろいきり』『しんぴのまもり』『ステルスロック』『どくびし』『ねばねばネット』『ひかりのかべ』『まきびし』『リフレクター』を入れ替える。経過ターン数は引き継がれる。"},"max-flare":{"n":739,"eff":"攻撃技のダイマックス技。5ターンの間、天気を『にほんばれ』にする。自分の命中率、相手の回避率に関係なく必ず命中する。レイドでは相手の不思議なバリアのゲージを2つ減らす。"},"max-flutterby":{"n":740,"eff":"攻撃技のダイマックス技。相手の『とくこう』ランクを1段階下げる。自分の命中率、相手の回避率に関係なく必ず命中する。レイドでは相手の不思議なバリアのゲージを2つ減らす。"},"max-lightning":{"n":741,"eff":"攻撃技のダイマックス技。5ターンの間、場の状態を『エレキフィールド』にする(地面にいるすべてのポケモンは、『ねむり』『あくび』状態にならず、また電気タイプの技の威力が1.3倍になる)。自分の命中率、相手の回避率に関係なく必ず命中する。レイドでは相手の不思議なバリアのゲージを2つ減らす。"},"max-strike":{"n":742,"eff":"攻撃技のダイマックス技。相手の『すばやさ』ランクを1段階下げる。自分の命中率、相手の回避率に関係なく必ず命中する。レイドでは相手の不思議なバリアのゲージを2つ減らす。"},"max-knuckle":{"n":743,"eff":"攻撃技のダイマックス技。自分と味方全体の『こうげき』ランクを1段階ずつ上げる。自分の命中率、相手の回避率に関係なく必ず命中する。レイドでは相手の不思議なバリアのゲージを2つ減らす。"},"max-phantasm":{"n":744,"eff":"攻撃技のダイマックス技。相手の『ぼうぎょ』ランクを1段階下げる。自分の命中率、相手の回避率に関係なく必ず命中する。レイドでは相手の不思議なバリアのゲージを2つ減らす。"},"max-hailstorm":{"n":745,"eff":"攻撃技のダイマックス技。5ターンの間、天気を『あられ』にする。自分の命中率、相手の回避率に関係なく必ず命中する。レイドでは相手の不思議なバリアのゲージを2つ減らす。"},"max-ooze":{"n":746,"eff":"攻撃技のダイマックス技。自分と味方全体の『とくこう』ランクを1段階ずつ上げる。自分の命中率、相手の回避率に関係なく必ず命中する。レイドでは相手の不思議なバリアのゲージを2つ減らす。"},"max-geyser":{"n":747,"eff":"攻撃技のダイマックス技。5ターンの間、天気を『あめ』にする。自分の命中率、相手の回避率に関係なく必ず命中する。レイドでは相手の不思議なバリアのゲージを2つ減らす。"},"max-airstream":{"n":748,"eff":"攻撃技のダイマックス技。自分と味方全体の『すばやさ』ランクを1段階ずつ上げる。自分の命中率、相手の回避率に関係なく必ず命中する。レイドでは相手の不思議なバリアのゲージを2つ減らす。"},"max-starfall":{"n":749,"eff":"攻撃技のダイマックス技。5ターンの間、場の状態を『ミストフィールド』にする(地面にいるすべてのポケモンは、状態異常にならず、またドラゴンタイプの技の受けるダメージが半減する)。自分の命中率、相手の回避率に関係なく必ず命中する。レイドでは相手の不思議なバリアのゲージを2つ減らす。"},"max-wyrmwind":{"n":750,"eff":"攻撃技のダイマックス技。相手の『こうげき』ランクを1段階下げる。自分の命中率、相手の回避率に関係なく必ず命中する。レイドでは相手の不思議なバリアのゲージを2つ減らす。"},"max-mindstorm":{"n":751,"eff":"攻撃技のダイマックス技。5ターンの間、場の状態を『サイコフィールド』にする(地面にいるすべてのポケモンは、相手の先制技を受けなくなり、またエスパータイプの技の威力が1.3倍になる)。自分の命中率、相手の回避率に関係なく必ず命中する。レイドでは相手の不思議なバリアのゲージを2つ減らす。"},"max-rockfall":{"n":752,"eff":"攻撃技のダイマックス技。5ターンの間、天気を『すなあらし』にする。自分の命中率、相手の回避率に関係なく必ず命中する。レイドでは相手の不思議なバリアのゲージを2つ減らす。"},"max-quake":{"n":753,"eff":"攻撃技のダイマックス技。自分と味方全体の『とくぼう』ランクを1段階ずつ上げる。自分の命中率、相手の回避率に関係なく必ず命中する。レイドでは相手の不思議なバリアのゲージを2つ減らす。"},"max-darkness":{"n":754,"eff":"攻撃技のダイマックス技。相手の『とくぼう』ランクを1段階下げる。自分の命中率、相手の回避率に関係なく必ず命中する。レイドでは相手の不思議なバリアのゲージを2つ減らす。"},"max-overgrowth":{"n":755,"eff":"攻撃技のダイマックス技。5ターンの間、場の状態を『グラスフィールド』にする(地面にいるすべてのポケモンは、毎ターン最大HPの1/16ずつ回復し、また草タイプの技の威力が1.3倍になる)。自分の命中率、相手の回避率に関係なく必ず命中する。レイドでは相手の不思議なバリアのゲージを2つ減らす。"},"max-steelspike":{"n":756,"eff":"攻撃技のダイマックス技。自分と味方全体の『ぼうぎょ』ランクを1段階ずつ上げる。自分の命中率、相手の回避率に関係なく必ず命中する。レイドでは相手の不思議なバリアのゲージを2つ減らす。"},"drum-beating":{"n":760,"eff":"100%の確率で相手の『すばやさ』ランクを1段階下げる。"},"pyro-ball":{"n":762,"eff":"10%の確率で相手を『やけど』状態にする。自分が『こおり』状態の時でも使う事ができ、使うと『こおり』状態が治る。弾技。"},"behemoth-blade":{"n":763,"eff":"通常攻撃。(第8世代では相手がダイマックスしていると、ダメージが2倍になる)切る技。"},"behemoth-bash":{"n":764,"eff":"通常攻撃。(第8世代では相手がダイマックスしていると、ダメージが2倍になる)"},"branch-poke":{"n":767,"eff":"通常攻撃。"},"overdrive":{"n":768,"eff":"相手全体が対象。音系の技。相手の『みがわり』状態を貫通する。"},"grav-apple":{"n":770,"eff":"100%の確率で相手の『ぼうぎょ』ランクを1段階下げる。場が『じゅうりょく』状態の時、威力が1.5倍になる。"},"strange-steam":{"n":772,"eff":"20%の確率で相手を1～4ターンの間『こんらん』状態にする。"},"obstruct":{"n":774,"eff":"必ず先制でき(優先度:+4)、そのターンの間、相手の攻撃技を受けない。また、接触技(直接攻撃)で攻撃してきた相手の『ぼうぎょ』ランクを2段階下げる。連続で使うと失敗しやすくなる。ダイマックス技は貫通し、1/4のダメージを受ける。"},"meteor-assault":{"n":776,"eff":"使用した次のターンは行動できない。"},"eternabeam":{"n":777,"eff":"使用した次のターンは行動できない。"},"jungle-healing":{"n":831,"eff":"自分と味方全体のHPが最大HPの1/4ずつ回復し、状態異常も回復する。"},"wicked-blow":{"n":832,"eff":"必ず急所に当たる。特性『てつのこぶし』の時、威力が1.2倍になる。パンチ系の技。"},"surging-strikes":{"n":833,"eff":"1ターンに3回連続で攻撃する。必ず急所に当たる。特性『てつのこぶし』の時、威力が1.2倍になる。パンチ系の技。"},"thunder-cage":{"n":834,"eff":"4～5ターンの間、毎ターン終了後最大HPの1/8のダメージを与え、その間タイプではない相手は逃げたり交代できない。"},"dragon-energy":{"n":835,"eff":"相手全体が対象。自分のHPが少ないほど技の威力が下がる。(150×自分の残りHP÷自分の最大HP)が威力。"},"freezing-glare":{"n":836,"eff":"10%の確率で相手を『こおり』状態にする。"},"fiery-wrath":{"n":837,"eff":"相手全体が対象。20%の確率で相手をひるませる。"},"thunderous-kick":{"n":838,"eff":"100%の確率で、相手の『ぼうぎょ』ランクを1段階下げる。"},"glacial-lance":{"n":839,"eff":"相手全体が対象。通常攻撃。"},"astral-barrage":{"n":840,"eff":"相手全体が対象。通常攻撃。"},"power-shift":{"n":844,"eff":"自分の『こうげき』と『ぼうぎょ』を入れ替える。『ランク』は変化しない。"},"springtide-storm":{"n":846,"eff":"相手全体が対象。30%の確率で相手の『こうげき』ランクを1段階下げる。風技。"},"mystical-power":{"n":847,"eff":"100%の確率で自分の『とくこう』ランクを1段階上げる。"},"chloroblast":{"n":850,"eff":"攻撃後、自分の最大HPの半分だけ自分もダメージを受ける。"},"victory-dance":{"n":852,"eff":"自分の『こうげき』『ぼうぎょ』『すばやさ』ランクを1段階ずつ上げる。踊り系の技。"},"esper-wing":{"n":855,"eff":"急所に当たりやすい(急所ランク:+1)。攻撃後、100%の確率で自分の『すばやさ』ランクが1段階上がる。"},"triple-arrows":{"n":858,"eff":"急所に当たりやすい(急所ランク:+1)。50%の確率で、相手の『ぼうぎょ』ランクを1段階下げる。30%の確率で相手をひるませる。"},"bleakwind-storm":{"n":861,"eff":"相手全体が対象。30%の確率で、相手の『すばやさ』ランクを1段階下げる。天気が『あめ』の時は必ず命中する。風技。"},"wildbolt-storm":{"n":862,"eff":"相手全体が対象。20%の確率で相手を『まひ』状態にする。天気が『あめ』の時は必ず命中する。風技。"},"sandsear-storm":{"n":863,"eff":"相手全体が対象。20%の確率で相手を『やけど』状態にする。天気が『あめ』の時は必ず命中する。風技。"},"lunar-blessing":{"n":864,"eff":"自分と味方全体のHPが最大HPの1/4ずつ回復し、状態異常も回復する。"},"take-heart":{"n":865,"eff":"自分の状態異常を治す。自分の『とくこう』『とくぼう』ランクが1段階ずつ上がる。"},"tera-blast":{"n":866,"eff":"自分がテラスタル状態の時、技のタイプが自分のテラスタイプになる。その際、この技の分類は、自分の攻撃と特攻の高い方となるため、『こうげき』のほうが高い場合は物理技となる。"},"silk-trap":{"n":867,"eff":"必ず先制でき(優先度:+4)、そのターンの間、相手の攻撃技を受けない。また、接触技(直接攻撃)で攻撃してきた相手の『すばやさ』ランクを1段階下げる。連続で使うと失敗しやすくなる。"},"order-up":{"n":871,"eff":"ダブルバトルでは口の中にいる味方のシャリタツの姿によって能力のランクが上がる。"},"spin-out":{"n":874,"eff":"攻撃後、自分の『すばやさ』ランクが2段階下がる。"},"glaive-rush":{"n":877,"eff":"次の自分のターンまで、相手から自分への攻撃が必ず命中し、受けるダメージが2倍になる。"},"revival-blessing":{"n":878,"eff":"手持ちの『ひんし』状態のポケモンを、最大HPの半分だけ回復させる。"},"triple-dive":{"n":880,"eff":"1ターンに3回連続で攻撃する。"},"doodle":{"n":882,"eff":"自分と味方を相手と同じ特性にする。"},"fillet-away":{"n":883,"eff":"自分のHPを最大HPの半分だけ減らす代わりに、自分の『こうげき』『とくこう』『すばやさ』ランクが2段階ずつ上がる。"},"psyblade":{"n":890,"eff":"場の状態が『エレキフィールド』の時、技の威力が1.5倍になる。切る技。"},"hydro-steam":{"n":891,"eff":"天気が『にほんばれ』の時、技の威力が下がらず、1.5倍になる。自分が『こおり』状態の時でも使う事ができ、使うと『こおり』状態が治る。また、相手の『こおり』状態を治す。"},"ruination":{"n":892,"eff":"相手のHPを残りHPの半分にする。タイプ相性の影響を受けない。"},"collision-course":{"n":893,"eff":"相手の弱点をつくと、ダメージが4/3倍(1.33倍)になる。"},"electro-drift":{"n":894,"eff":"相手の弱点をつくと、ダメージが4/3倍(1.33倍)になる。"},"hyper-drill":{"n":902,"eff":"相手の『まもる』『みきり』などの効果を受けない。"},"double-shock":{"n":907,"eff":"攻撃後、自分はタイプではなくなる。自分がタイプではない時は失敗する。"},"blazing-torque":{"n":911,"eff":"スター団専用技。30%の確率で、相手を『やけど』状態にする。"},"wicked-torque":{"n":912,"eff":"スター団専用技。10%の確率で、相手を『ねむり』状態にする。"},"noxious-torque":{"n":913,"eff":"スター団専用技。30%の確率で、相手を『どく』状態にする。"},"combat-torque":{"n":914,"eff":"スター団専用技。30%の確率で、相手を『まひ』状態にする。"},"magical-torque":{"n":915,"eff":"スター団専用技。30%の確率で、相手を『こんらん』状態にする。"},"blood-moon":{"n":916,"eff":"この技は2回連続で出すことができない。"},"ivy-cudgel":{"n":919,"eff":"『オーガポン』が使う場合、持たせた「おめん」によるフォルムに合わせて、技がタイプのいずれかに変化する。また、急所に当たりやすい(急所ランク:+1)。"},"tera-starstorm":{"n":921,"eff":"『テラパゴス(ステラ)』がステラフォルムの時に使用すると、相手全体が攻撃対象となり、また技のタイプが『ステラ』タイプになる(テラスタルしている相手にはダメージが2倍、その他は1倍)。その際、この技の分類は、自分の攻撃と特攻の高い方となる。"},"burning-bulwark":{"n":923,"eff":"必ず先制でき(優先度:+4)、そのターンの間、相手の攻撃技を受けない。また、接触技(直接攻撃)で攻撃してきた相手を『やけど』状態にする。連続で使うと失敗しやすくなる。"},"thunderclap":{"n":924,"eff":"必ず先制できる(優先度:+1)。そのターン相手が選んだ技が攻撃技ではない場合や、すでに攻撃を終えていた場合は失敗する。"},"mighty-cleave":{"n":925,"eff":"相手の『まもる』『みきり』などの効果を受けない。切る技。"},"tachyon-cutter":{"n":926,"eff":"1ターンに2回連続で攻撃する。自分の命中率、相手の回避率に関係なく必ず命中する。切る技。"},"malignant-chain":{"n":934,"eff":"50%の確率で相手を『もうどく』状態にする。"}}